gaode_mcp_server/__main__.py
gaode_mcp_server/src/config.py
gaode_mcp_server/src/gaode_server.py
gaode_mcp_server/src/amap/__init__.py
gaode_mcp_server/src/amap/client.py
gaode_mcp_server/src/amap/errors.py
gaode_mcp_server/src/amap/geo.py
gaode_mcp_server/src/amap/ip.py
gaode_mcp_server/src/amap/poi.py
gaode_mcp_server/src/amap/route.py
gaode_mcp_server/src/amap/weather.py
gaode_mcp_server/src/utils/tool_wrapper.py
gaode_mcp_server-0.1.2.dist-info/METADATA
gaode_mcp_server-0.1.2.dist-info/WHEEL
gaode_mcp_server-0.1.2.dist-info/entry_points.txt
gaode_mcp_server-0.1.2.dist-info/top_level.txt
gaode_mcp_server-0.1.2.dist-info/RECORD
